bogohash/__init__.py
bogohash/tests.py
bogohash-0.1.dist-info/LICENSE
bogohash-0.1.dist-info/METADATA
bogohash-0.1.dist-info/WHEEL
bogohash-0.1.dist-info/top_level.txt
bogohash-0.1.dist-info/RECORD
